[
    {
        "main_category": "Bếp",
        "products": [
            {
                "product_name": "Starbucks |Chính Hãng| Blackpink - Bst Bình Nước, Ly Giữ Nhiệt, Cốc Thuỷ Tinh Sứ",
                "product_price": 1400000,
                "product_store": "Starbuck Dreamers",
                "product_image": "https://p-vn.ipricegroup.com/2e3a24ff713585971829ee7fb5da8ea0feace60e_0.jpg",
                "product_link": "https://shopee.vn/buyer/login?next=https%3A%2F%2Fshopee.vn%2Fproduct%2F39996130%2F22474899775%3Fuls_trackid%3D51nd332001qs%26utm_campaign%3D-%26utm_content%3D----igtttttttttttttttttttttttttttttt8q10ivi5~001Gq0hZ%26utm_medium%3Daffiliates%26utm_source%3Dan_17202000000%26utm_term%3Dcdmcwe28p6j1"
            },
            {
                "product_name": "Starbucks [Chính Hãng] Bst Ly Giữ Nhiệt Secret Eden 2024 Sakura Blossoms Vietnam",
                "product_price": 630000,
                "product_store": "ninguyengv",
                "product_image": "https://p-vn.ipricegroup.com/155b67c5c0b7856ae9c6658bf9a4247bffb75eab_0.jpg",
                "product_link": "https://shopee.vn/buyer/login?next=https%3A%2F%2Fshopee.vn%2Fproduct%2F63137506%2F24564505448%3Fuls_trackid%3D51nd342800qs%26utm_campaign%3D-%26utm_content%3D----igttttttttttttttttttttttttttttttbcrdu90q~001Gq0hZ%26utm_medium%3Daffiliates%26utm_source%3Dan_17202000000%26utm_term%3Dcdmcx82tidu1"
            },
            {
                "product_name": "Pandora Hạt Vòng Charm Spatula Frying Pan Whisk Dangle 799531C01 Màu Bạc",
                "product_price": 1490000,
                "product_store": "VuaHangHieu",
                "product_image": "https://p-vn.ipricegroup.com/7091dc61049287cefcec95428d7ece001520936d_0.jpg",
                "product_link": "https://vuahanghieu.com/hat-vong-charm-pandora-spatula-frying-pan-whisk-dangle-799531c01-mau-bac-ph053312?source=igttttttttttttttttttttttttttttttdxtl7gl0~001Fl0hZ&trans_id=%7Btransaction_id%7D&utm_source=iprice"
            },
            {
                "product_name": "Starbucks Ly Giữ Nhiệt Korea Bst Sakura",
                "product_price": 830000,
                "product_store": "TieuyeuSbux",
                "product_image": "https://p-vn.ipricegroup.com/f105f4eacfdfd8ba89d941609914fb6d9b8fdee2_0.jpg",
                "product_link": "https://shopee.vn/buyer/login?next=https%3A%2F%2Fshopee.vn%2Fproduct%2F301306793%2F23323456328%3Fuls_trackid%3D51nd360300qs%26utm_campaign%3D-%26utm_content%3D----igtttttttttttttttttttttttttttttt437aoy4~~001Gq0hZ%26utm_medium%3Daffiliates%26utm_source%3Dan_17202000000%26utm_term%3Dcdmcyssf7991"
            },
            {
                "product_name": "Starbucks [ US] - LY GIỮ LẠNH BLING TEAL GREEN STUDDED COLD CUP 24 Oz",
                "product_price": 790000,
                "product_store": "callmebysbuxx",
                "product_image": "https://p-vn.ipricegroup.com/29fa06c1e13b4e6894e3c30f0f83056d70015afd_0.jpg",
                "product_link": "https://www.lazada.vn/products/starbucks-us-ly-giu-lanh-bling-teal-green-studded-cold-cup-24-oz-i2522140373-s12362334511.html?trafficFrom=17449020_303586&laz_trackid=2:mm_150021224_51253421_2010203413:clkgikv4a1iha304mtqi28&mkttid=clkgikv4a1iha304mtqi28"
            },
            {
                "product_name": "Yamaha Full Bộ Nồi Trước + Sau Như Hình (Sirius + Jupiter R + Jupiter V + Jupiter Ravita Từ Vuông Zin Hãng Exedy",
                "product_price": 1730000,
                "product_store": "Trương Trung",
                "product_image": "https://p-vn.ipricegroup.com/f9f03fbd94a8d31502db39b7c861fd03d3f0561f_0.jpg",
                "product_link": "https://shopee.vn/buyer/login?next=https%3A%2F%2Fshopee.vn%2Fproduct%2F906667059%2F18874621517%3Fuls_trackid%3D51nd384o00rk%26utm_campaign%3D-%26utm_content%3D----igtttttttttttttttttttttttttttttt8g2rltk1~001Gq0hZ%26utm_medium%3Daffiliates%26utm_source%3Dan_17202000000%26utm_term%3Dcdmd1jdfbb5y"
            },
            {
                "product_name": "Bear Bình Giữ Nhiệt BWB2007 Màu Hồng 500ml",
                "product_price": 272000,
                "product_store": "VuaHangHieu",
                "product_image": "https://p-vn.ipricegroup.com/5e5324d9f0f9f8ebc7c8e2e360d18aa48c179ed0_0.jpg",
                "product_link": "https://vuahanghieu.com/binh-giu-nhiet-ttwn-bear-bwb2007-mau-hong-500ml-ph151136?source=igttttttttttttttttttttttttttttttcdfmmtfv~001Fl0hZ&trans_id=%7Btransaction_id%7D&utm_source=iprice"
            },
            {
                "product_name": "Khăn Trải Bàn Hình Chữ Nhật Bằng Pvc Chống Thấm Nước/Dầu/Bỏng Dùng Một Lần Tiện Lợi",
                "product_price": 142800,
                "product_store": "Creativehomelife.vn",
                "product_image": "https://p-vn.ipricegroup.com/4ee814b7a3e117d72ef46cc039af193f5a22ee5c_0.jpg",
                "product_link": "https://shopee.vn/buyer/login?next=https%3A%2F%2Fshopee.vn%2Fproduct%2F379238908%2F15776463354%3Fuls_trackid%3D51nd39j900qs%26utm_campaign%3D-%26utm_content%3D----igttttttttttttttttttttttttttttttbw80u0ub~001Gq0hZ%26utm_medium%3Daffiliates%26utm_source%3Dan_17202000000%26utm_term%3Dcdmd2qvxek2s"
            },
            {
                "product_name": "Tupperware CHẢO 24cm UNIVERSAL COOKWARE VIỆT (CÓ NẮP)",
                "product_price": 1290000,
                "product_store": "HAPPY BẾP",
                "product_image": "https://p-vn.ipricegroup.com/ef03fe15cdaa26e5406fca6f039d4efc6acdbbef_0.jpg",
                "product_link": "https://www.lazada.vn/products/chao-24cm-universal-cookware-tupperware-viet-co-nap-i2265370719-s10936473862.html?trafficFrom=17449020_303586&laz_trackid=2:mm_150021224_51253421_2010203413:clkgg5u631iha318j6omgh&mkttid=clkgg5u631iha318j6omgh"
            },
            {
                "product_name": "SENTANO [SALE RẺ]Combo Chậu rửa chén bồn rửa chén đúc liền khối 2 hộc 8245 LỆCH inox 304 +Vòi rửa chén lạnh tròn (thân ống fi18) TẶNG rổ inox đa năng",
                "product_price": 849000,
                "product_store": "Nội Thất Inox Ngọc Thịnh",
                "product_image": "https://p-vn.ipricegroup.com/7c1116a5fc835734b3b71c0e0e6bb048607b7f9e_0.jpg",
                "product_link": "https://www.lazada.vn/products/sale-recombo-chau-rua-chen-bon-rua-chen-duc-lien-khoi-2-hoc-8245-lech-inox-304-voi-rua-chen-lanh-tron-than-ong-fi18-tang-ro-inox-da-nang-i775142357-s4641395773.html?trafficFrom=17449020_303586&laz_trackid=2:mm_150021224_51253421_2010203413:clkgl3s7a1iha31g8rojep&mkttid=clkgl3s7a1iha31g8rojep"
            },
            {
                "product_name": "Bear Bình Nước Giữ Nhiệt BWB 20077050 Màu Kem 500ml",
                "product_price": 272000,
                "product_store": "VuaHangHieu",
                "product_image": "https://p-vn.ipricegroup.com/41c1686f850ff9343471dc75d976e5be6069138f_0.jpg",
                "product_link": "https://vuahanghieu.com/binh-nuoc-giu-nhiet-ttwn-bear-bwb-20077050-mau-kem-500ml-ph098681?source=igtttttttttttttttttttttttttttttt69xqlpn3~001Fl0hZ&trans_id=%7Btransaction_id%7D&utm_source=iprice"
            },
            {
                "product_name": "SYM Full bộ nồi( bộ côn ) trước dùng cho dòng xe máy tay ga Elites 50cc .hàng sin do công ty đài loan sản xuất.",
                "product_price": 1400000,
                "product_store": "Dung loc 1616310713",
                "product_image": "https://p-vn.ipricegroup.com/56ca52f3b6124536e2b2c6877f14802e0d3b0adf_0.jpg",
                "product_link": "https://www.lazada.vn/products/full-bo-noi-bo-con-truoc-dung-cho-dong-xe-may-tay-ga-sym-elites-50cc-hang-sin-do-cong-ty-dai-loan-sym-san-xuat-i2127240098-s10018014559.html?trafficFrom=17449020_303586&laz_trackid=2:mm_150021224_51253421_2010203413:clkgl3tvk1iha322kn8aao&mkttid=clkgl3tvk1iha322kn8aao"
            },
            {
                "product_name": "F.C.C Bộ Nồi Tay Ga 10 Món Chính Hãng Cho Xe Airblade 110, Ab 125 150, Vairo Pcx Sh Vision Lead Click",
                "product_price": 1200000,
                "product_store": "Cửa Hàng Trạm Xe 1368",
                "product_image": "https://p-vn.ipricegroup.com/dec848469a4f78826a33ed6f15511bb2e180d196_0.jpg",
                "product_link": "https://shopee.vn/buyer/login?next=https%3A%2F%2Fshopee.vn%2Fproduct%2F132756242%2F7886693929%3Fuls_trackid%3D51nd3duq00qs%26utm_campaign%3D-%26utm_content%3D----igttttttttttttttttttttttttttttttc1e7uxgl~001Gq0hZ%26utm_medium%3Daffiliates%26utm_source%3Dan_17202000000%26utm_term%3Dcdmd6b4g71ju"
            },
            {
                "product_name": "Starbucks [Authentic] EU LY GIỮ NHIỆT 473ML STAINLESS STEEL COLD CUP",
                "product_price": 1250000,
                "product_store": "Goblin Starbucks Store",
                "product_image": "https://p-vn.ipricegroup.com/e545ed2e1298b00e9867a52cd8902ddc966fdb7c_0.jpg",
                "product_link": "https://www.lazada.vn/products/authentic-starbucks-eu-ly-giu-nhiet-473ml-stainless-steel-cold-cup-i2426649142-s11974784706.html?trafficFrom=17449020_303586&laz_trackid=2:mm_150021224_51253421_2010203413:clkgislgd1iha32ka9945h&mkttid=clkgislgd1iha32ka9945h"
            },
            {
                "product_name": "Xửng Hấp Tupperware 2 Tầng Steam It Hàng Chính Hãng",
                "product_price": 319000,
                "product_store": "306643",
                "product_image": "https://p-vn.ipricegroup.com/81d5a958ff36e6144f7f2ac07930db5ab88093f4_0.jpg",
                "product_link": "https://tiki.vn/xung-hap-tupperware-2-tang-steam-it-p248078141.html?spid=248078142&utm_source=iprice.vn&utm_medium=tiki-aff&utm_campaign=AFF_NBR_IPR_UNK_TIKIVN-17FCWZZE_ALL_VN_ALL_UNK_UNK_TAPX.58f86df1-beb8-498c-b56f-1565af399ec0_TAPU.9cbabb48-212d-4930-bef0-ae555f53d833&utm_term=TAPM.igtttttttttttttttttttttttttttttt2ltqyq26%7E001Nb0hZ_TAPP.iprice_TAPT.TI2&trans_id=%7Btransaction_id%7D&tclid=313ea0ca-650e-4a89-a2ea-a47942547082&fsl=true&isOpenStore=false&trackId=678218f4a91e24f18defa000&osName=Windows&deepLink=tikivn%3A%2F%2Fproducts%2F248078141%3Fspid%3D248078142%26utm_source%3Diprice.vn%26utm_medium%3Dtiki-aff%26utm_campaign%3DAFF_NBR_IPR_UNK_TIKIVN-17FCWZZE_ALL_VN_ALL_UNK_UNK_TAPX.58f86df1-beb8-498c-b56f-1565af399ec0_TAPU.9cbabb48-212d-4930-bef0-ae555f53d833%26utm_term%3DTAPM.igtttttttttttttttttttttttttttttt2ltqyq26%257E001Nb0hZ_TAPP.iprice_TAPT.TI2%26trans_id%3D%257Btransaction_id%257D%26tclid%3D313ea0ca-650e-4a89-a2ea-a47942547082&clickId=4cd83e8e-be39-414d-bc41-637f2350285e&fullUrl=https%3A%2F%2Fti.ki%2F2sS%2F17FCWZZE%3Futm_term%3DTAPM.igtttttttttttttttttttttttttttttt2ltqyq26%7E001Nb0hZ_TAPP.iprice_TAPT.TI2%26TIKI_URI%3Dhttps%253A%252F%252Ftiki.vn%252Fxung-hap-tupperware-2-tang-steam-it-p248078141.html%253Fspid%253D248078142%26utm_source%3Diprice%26trans_id%3D%257Btransaction_id%257D&isFBApp=false&deepLinkData=&hash=17FCWZZE"
            },
            {
                "product_name": "Starbucks Ly Giữ Nhiệt SB Cold Cup 24Oz 750ml Màu Xanh Mint - Sang Trọng Tiện Lợi Fullbox",
                "product_price": 129000,
                "product_store": "RVG Store",
                "product_image": "https://p-vn.ipricegroup.com/cadabd1199d87664dbe9e4f76d6593370f733577_0.jpg",
                "product_link": "https://www.lazada.vn/products/ly-giu-nhiet-sb-cold-cup-24oz-750ml-mau-xanh-mint-sang-trong-tien-loi-fullbox-i2647598407-s12916902574.html?trafficFrom=17449020_303586&laz_trackid=2:mm_150021224_51253421_2010203413:clkgikp0p1iha3382n8kjk&mkttid=clkgikp0p1iha3382n8kjk"
            },
            {
                "product_name": "Yamaha Full Bộ Nồi Chống Trượt R15V3 Chính Hãng Indo Gắn Cho Exciter 135 150, Fz 150, Tfx 150, R15V2",
                "product_price": 2580000,
                "product_store": "Nồi Xe Côn Tay",
                "product_image": "https://p-vn.ipricegroup.com/a06afbe41e6f08ae94cc044ae47e9270a508801c_0.jpg",
                "product_link": "https://shopee.vn/buyer/login?next=https%3A%2F%2Fshopee.vn%2Fproduct%2F479561785%2F7294178413%3Fuls_trackid%3D51nd3hvr0025%26utm_campaign%3D-%26utm_content%3D----igttttttttttttttttttttttttttttttuj993h4~~001Gq0hZ%26utm_medium%3Daffiliates%26utm_source%3Dan_17202000000%26utm_term%3Dcdmd9m8cuef1"
            },
            {
                "product_name": "Zebra Bộ Nồi Inox 304 - Sản Xuất Tại Thái Lan - Extreme Infinity 0.6Mm (18+20+22Cm) 180827",
                "product_price": 1180000,
                "product_store": "Giadungnho.com",
                "product_image": "https://p-vn.ipricegroup.com/95c3ab05c1cfa1fb0fbe204701cef5d45937967c_0.jpg",
                "product_link": "https://shopee.vn/buyer/login?next=https%3A%2F%2Fshopee.vn%2Fproduct%2F51969047%2F5260288406%3Fuls_trackid%3D51nd3j0100rk%26utm_campaign%3D-%26utm_content%3D----igtttttttttttttttttttttttttttttt58yox9td~001Gq0hZ%26utm_medium%3Daffiliates%26utm_source%3Dan_17202000000%26utm_term%3Dcdmdaf6n6x47"
            },
            {
                "product_name": "Bộ Kệ Bếp Tupperware Modular Mates Starter Nhựa Nguyên Sinh",
                "product_price": 598000,
                "product_store": "306643",
                "product_image": "https://p-vn.ipricegroup.com/fae2f80643f7cb26a82e254f38d438f85b23a9e3_0.jpg",
                "product_link": "https://tiki.vn/bo-ke-bep-tupperware-modular-mates-starter-nhua-nguyen-sinh-p275589307.html?spid=275589308&utm_source=iprice.vn&utm_medium=tiki-aff&utm_campaign=AFF_NBR_IPR_UNK_TIKIVN-17FCWZZE_ALL_VN_ALL_UNK_UNK_TAPX.58f86df1-beb8-498c-b56f-1565af399ec0_TAPU.9cbabb48-212d-4930-bef0-ae555f53d833&utm_term=TAPM.igttttttttttttttttttttttttttttttacn0nmah%7E001Nb0hZ_TAPP.iprice_TAPT.TI2&trans_id=%7Btransaction_id%7D&tclid=f069c15c-11e6-4c93-bd8e-c39835cf010d&fsl=true&isOpenStore=false&trackId=6782191d04eb5adace0f2131&osName=Windows&deepLink=tikivn%3A%2F%2Fproducts%2F275589307%3Fspid%3D275589308%26utm_source%3Diprice.vn%26utm_medium%3Dtiki-aff%26utm_campaign%3DAFF_NBR_IPR_UNK_TIKIVN-17FCWZZE_ALL_VN_ALL_UNK_UNK_TAPX.58f86df1-beb8-498c-b56f-1565af399ec0_TAPU.9cbabb48-212d-4930-bef0-ae555f53d833%26utm_term%3DTAPM.igttttttttttttttttttttttttttttttacn0nmah%257E001Nb0hZ_TAPP.iprice_TAPT.TI2%26trans_id%3D%257Btransaction_id%257D%26tclid%3Df069c15c-11e6-4c93-bd8e-c39835cf010d&clickId=4b47ae85-ba91-4777-af08-96ef39889db6&fullUrl=https%3A%2F%2Fti.ki%2F2sS%2F17FCWZZE%3Futm_term%3DTAPM.igttttttttttttttttttttttttttttttacn0nmah%7E001Nb0hZ_TAPP.iprice_TAPT.TI2%26TIKI_URI%3Dhttps%253A%252F%252Ftiki.vn%252Fbo-ke-bep-tupperware-modular-mates-starter-nhua-nguyen-sinh-p275589307.html%253Fspid%253D275589308%26utm_source%3Diprice%26trans_id%3D%257Btransaction_id%257D&isFBApp=false&deepLinkData=&hash=17FCWZZE"
            },
            {
                "product_name": "DUY TAN Kệ Chén Matsu Duy Tân Có Nắp Đậy",
                "product_price": 379000,
                "product_store": "GIAO HÀNG HỎA TỐC.VN",
                "product_image": "https://p-vn.ipricegroup.com/85f0164e237087bb4bcd943e925c8bb324864f88_0.jpg",
                "product_link": "https://shopee.vn/buyer/login?next=https%3A%2F%2Fshopee.vn%2Fproduct%2F571893264%2F14722345144%3Fuls_trackid%3D51nd3kuo00qs%26utm_campaign%3D-%26utm_content%3D----igttttttttttttttttttttttttttttttd9jr0bq6~001Gq0hZ%26utm_medium%3Daffiliates%26utm_source%3Dan_17202000000%26utm_term%3Dcdmdc1p13afh"
            },
            {
                "product_name": "DUY TAN Kệ Chén Nhựa Duy Tân Có Nắp",
                "product_price": 375000,
                "product_store": "Bảo Ngọc Duy Tân",
                "product_image": "https://p-vn.ipricegroup.com/a95e962de1f71757cc881e93c04759759cb965a0_0.jpg",
                "product_link": "https://shopee.vn/buyer/login?next=https%3A%2F%2Fshopee.vn%2Fproduct%2F62609082%2F20707000072%3Fuls_trackid%3D51nd3lnl0025%26utm_campaign%3D-%26utm_content%3D----igtttttttttttttttttttttttttttttt8bvuyh6a~001Gq0hZ%26utm_medium%3Daffiliates%26utm_source%3Dan_17202000000%26utm_term%3Dcdmdcobgrndu"
            },
            {
                "product_name": "Kim Hằng Chảo bầu quantum chống dính an toàn sức khỏe tiện dụng màu sắc trang nhã Chính hãng",
                "product_price": 1042200,
                "product_store": "Gia Dụng Bảo Phát -Huyên Bùi",
                "product_image": "https://p-vn.ipricegroup.com/e2c5831a008352e4198c6ea2944ba0ed9522092f_0.jpg",
                "product_link": "https://www.lazada.vn/products/chao-bau-quantum-chong-dinh-an-toan-suc-khoe-tien-dung-mau-sac-trang-nha-kim-hang-chinh-hang-i1675094696-s8543880123.html?trafficFrom=17449020_303586&laz_trackid=2:mm_150021224_51253421_2010203413:clkgislgd1iha3536o9nhd&mkttid=clkgislgd1iha3536o9nhd"
            },
            {
                "product_name": "Chảo Tupperware Chống Dính Tự Nhiên Universal Cookware Frypan 24Cm",
                "product_price": 1198800,
                "product_store": "306643",
                "product_image": "https://p-vn.ipricegroup.com/60b347d82193efd7ee8b37855de98054126cf4a2_0.jpg",
                "product_link": "https://tiki.vn/xung-hap-3-tang-steam-it-tupperware-p213516346.html?spid=213516347&utm_source=iprice.vn&utm_medium=tiki-aff&utm_campaign=AFF_NBR_IPR_UNK_TIKIVN-17FCWZZE_ALL_VN_ALL_UNK_UNK_TAPX.58f86df1-beb8-498c-b56f-1565af399ec0_TAPU.9cbabb48-212d-4930-bef0-ae555f53d833&utm_term=TAPM.igtttttttttttttttttttttttttttttt8hmefj0v%7E001Nb0hZ_TAPP.iprice_TAPT.TI2&trans_id=%7Btransaction_id%7D&tclid=4e73b4c4-5a79-4264-8974-3e4d6d71ca9d&fsl=true&isOpenStore=false&trackId=678219444cb8b9f42c6ba8ec&osName=Windows&deepLink=tikivn%3A%2F%2Fproducts%2F213516346%3Fspid%3D213516347%26utm_source%3Diprice.vn%26utm_medium%3Dtiki-aff%26utm_campaign%3DAFF_NBR_IPR_UNK_TIKIVN-17FCWZZE_ALL_VN_ALL_UNK_UNK_TAPX.58f86df1-beb8-498c-b56f-1565af399ec0_TAPU.9cbabb48-212d-4930-bef0-ae555f53d833%26utm_term%3DTAPM.igtttttttttttttttttttttttttttttt8hmefj0v%257E001Nb0hZ_TAPP.iprice_TAPT.TI2%26trans_id%3D%257Btransaction_id%257D%26tclid%3D4e73b4c4-5a79-4264-8974-3e4d6d71ca9d&clickId=552e9be6-b724-4cab-a981-32866918459e&fullUrl=https%3A%2F%2Fti.ki%2F2sS%2F17FCWZZE%3Futm_term%3DTAPM.igtttttttttttttttttttttttttttttt8hmefj0v%7E001Nb0hZ_TAPP.iprice_TAPT.TI2%26TIKI_URI%3Dhttps%253A%252F%252Ftiki.vn%252Fxung-hap-3-tang-steam-it-tupperware-p213516346.html%253Fspid%253D213516347%26utm_source%3Diprice%26trans_id%3D%257Btransaction_id%257D&isFBApp=false&deepLinkData=&hash=17FCWZZE"
            },
            {
                "product_name": "Fcc Full bộ nồi trước nồi sau và dây curoa Honda AirBlade 125cc - Bộ nồi xe AB125",
                "product_price": 1700000,
                "product_store": "RACING BOY",
                "product_image": "https://p-vn.ipricegroup.com/8b0defcfdfe05604b88c583785acdcd65767d374_0.jpg",
                "product_link": "https://www.lazada.vn/products/full-bo-noi-truoc-noi-sau-va-day-curoa-honda-airblade-125cc-bo-noi-xe-ab125-i275298740-s422752421.html?trafficFrom=17449020_303586&laz_trackid=2:mm_150021224_51253421_2010203413:clkgk21gn1iha35l0j95sc&mkttid=clkgk21gn1iha35l0j95sc"
            },
            {
                "product_name": "KHĂN TRẢI BÀN LỤA 3D in nổi sang trọng không thấm - Bàn tròn bàn vuông",
                "product_price": 57000,
                "product_store": "khosithuduc",
                "product_image": "https://p-vn.ipricegroup.com/de1622dbfeac538f81852a56357fe1efb73caccd_0.jpg",
                "product_link": "https://www.lazada.vn/products/khan-trai-ban-lua-3d-in-noi-sang-trong-khong-tham-ban-tron-ban-vuong-i2509709877-s12299465985.html?trafficFrom=17449020_303586&laz_trackid=2:mm_150021224_51253421_2010203413:clkgg5qhu1iha35vsh968e&mkttid=clkgg5qhu1iha35vsh968e"
            },
            {
                "product_name": "[Hàng Đẹp] Khăn Trải Bàn Nhựa Pvc Cắt Theo Yêu Cầu Đủ Kích Thước - Dày Dặn Chống Thấm Nước",
                "product_price": 150000,
                "product_store": "Jacky Decor - Khăn trải bàn",
                "product_image": "https://p-vn.ipricegroup.com/9fd4cee4e463eb8793d7c87829f456fc7da279ea_0.jpg",
                "product_link": "https://shopee.vn/buyer/login?next=https%3A%2F%2Fshopee.vn%2Fproduct%2F9516713%2F17491929244%3Fuls_trackid%3D51nd3qll00qs%26utm_campaign%3D-%26utm_content%3D----igtttttttttttttttttttttttttttttt6m943q4h~001Gq0hZ%26utm_medium%3Daffiliates%26utm_source%3Dan_17202000000%26utm_term%3Dcdmdgpkrahmy"
            },
            {
                "product_name": "Bình Giữ Nhiệt Tupperware Xploris Plask 450Ml",
                "product_price": 649000,
                "product_store": "306643",
                "product_image": "https://p-vn.ipricegroup.com/ff50ec62d44c0438e080f256925d33bae7835e63_0.jpg",
                "product_link": "https://tiki.vn/binh-giu-nhiet-tupperware-xploris-plask-450ml-p275672629.html?spid=275672633&utm_source=iprice.vn&utm_medium=tiki-aff&utm_campaign=AFF_NBR_IPR_UNK_TIKIVN-17FCWZZE_ALL_VN_ALL_UNK_UNK_TAPX.58f86df1-beb8-498c-b56f-1565af399ec0_TAPU.9cbabb48-212d-4930-bef0-ae555f53d833&utm_term=TAPM.igttttttttttttttttttttttttttttttaufr7emg%7E001Nb0hZ_TAPP.iprice_TAPT.TI2&trans_id=%7Btransaction_id%7D&tclid=07e3d958-1bda-4745-8b54-90f7df14d9a6&fsl=true&isOpenStore=false&trackId=6782196e0d84f4d1dc7f49cd&osName=Windows&deepLink=tikivn%3A%2F%2Fproducts%2F275672629%3Fspid%3D275672633%26utm_source%3Diprice.vn%26utm_medium%3Dtiki-aff%26utm_campaign%3DAFF_NBR_IPR_UNK_TIKIVN-17FCWZZE_ALL_VN_ALL_UNK_UNK_TAPX.58f86df1-beb8-498c-b56f-1565af399ec0_TAPU.9cbabb48-212d-4930-bef0-ae555f53d833%26utm_term%3DTAPM.igttttttttttttttttttttttttttttttaufr7emg%257E001Nb0hZ_TAPP.iprice_TAPT.TI2%26trans_id%3D%257Btransaction_id%257D%26tclid%3D07e3d958-1bda-4745-8b54-90f7df14d9a6&clickId=6903cdd6-b0b7-48ac-a99e-e4cf18150daa&fullUrl=https%3A%2F%2Fti.ki%2F2sS%2F17FCWZZE%3Futm_term%3DTAPM.igttttttttttttttttttttttttttttttaufr7emg%7E001Nb0hZ_TAPP.iprice_TAPT.TI2%26TIKI_URI%3Dhttps%253A%252F%252Ftiki.vn%252Fbinh-giu-nhiet-tupperware-xploris-plask-450ml-p275672629.html%253Fspid%253D275672633%26utm_source%3Diprice%26trans_id%3D%257Btransaction_id%257D&isFBApp=false&deepLinkData=&hash=17FCWZZE"
            },
            {
                "product_name": "Lock&Lock Bình giữ nhiệt Bucket Tumbler - LHC4269 - Có quai xách tiện lợi - Thép không gỉ SUS304 - Đế chống trượt",
                "product_price": 262000,
                "product_store": "Lock&amp;Lock Flagship Store",
                "product_image": "https://p-vn.ipricegroup.com/cdbc6d9a8b6174dbe6507533c04a516000b39d54_0.jpg",
                "product_link": "https://www.lazada.vn/products/binh-giu-nhiet-locklock-bucket-tumbler-lhc4269-co-quai-xach-tien-loi-thep-khong-gi-sus304-de-chong-truot-i1308202214-s5074607816.html?trafficFrom=17449020_303586&laz_trackid=2:mm_150021224_51253421_2010203413:clkgg5or91iha36v95q2hn&mkttid=clkgg5or91iha36v95q2hn"
            },
            {
                "product_name": "Corelle Tô Thủy Tinh Winter Frost White 1.0Lit 432-N-Lp",
                "product_price": 450000,
                "product_store": "Cty Thương Mại Quốc Tế T.M.T",
                "product_image": "https://p-vn.ipricegroup.com/5c87d75f093a5bfda23ef20706e71e09a072ba8e_0.jpg",
                "product_link": "https://shopee.vn/verify/traffic/error?home_url=https%3A%2F%2Fshopee.vn&is_logged_in=false&tracking_id=5175ee9740e-97a4-4f32-9e5c-979561b975b7"
            },
            {
                "product_name": "SENTANO [SALE RẺ][HÀNG DÀY ĐẸP] COMBO Chậu rửa chén NANO ĐEN 2 hố LỆCH 82x45cm phủ nano đen chống trầy",
                "product_price": 1146000,
                "product_store": "Nội Thất Inox Ngọc Thịnh",
                "product_image": "https://p-vn.ipricegroup.com/e0b1bbdee1d9f449c7cede9c2150e554adf26c62_0.jpg",
                "product_link": "https://www.lazada.vn/products/sale-rehang-day-dep-combo-chau-rua-chen-nano-den-2-ho-lech-sentano-82x45cm-phu-nano-den-chong-tray-i1318323589-s5220571631.html?trafficFrom=17449020_303586&laz_trackid=2:mm_150021224_51253421_2010203413:clkgl3rs91iha37jscseb1&mkttid=clkgl3rs91iha37jscseb1"
            },
            {
                "product_name": "Máy Xay Thịt Xay Thực Phẩm Đa Năng Tefal Mb520138 Hàng Chính Hãng",
                "product_price": 1092500,
                "product_store": "2172",
                "product_image": "https://p-vn.ipricegroup.com/91fc6c3324680423949fe3ec520e6967e82418c2_0.jpg",
                "product_link": "https://tiki.vn/may-xay-thit-xay-thuc-pham-da-nang-tefal-mb520138-hang-chinh-hang-p124116795.html?spid=172920243&utm_source=iprice.vn&utm_medium=tiki-aff&utm_campaign=AFF_NBR_IPR_UNK_TIKIVN-17FCWZZE_ALL_VN_ALL_UNK_UNK_TAPX.58f86df1-beb8-498c-b56f-1565af399ec0_TAPU.9cbabb48-212d-4930-bef0-ae555f53d833&utm_term=TAPM.igttttttttttttttttttttttttttttttcnbhnrox%7E001Nb0hZ_TAPP.iprice_TAPT.TI2&trans_id=%7Btransaction_id%7D&tclid=ca5add0c-9def-4d78-bf29-cdddd3defa5f&fsl=true&isOpenStore=false&trackId=67821996a91e24f18defa0e6&osName=Windows&deepLink=tikivn%3A%2F%2Fproducts%2F124116795%3Fspid%3D172920243%26utm_source%3Diprice.vn%26utm_medium%3Dtiki-aff%26utm_campaign%3DAFF_NBR_IPR_UNK_TIKIVN-17FCWZZE_ALL_VN_ALL_UNK_UNK_TAPX.58f86df1-beb8-498c-b56f-1565af399ec0_TAPU.9cbabb48-212d-4930-bef0-ae555f53d833%26utm_term%3DTAPM.igttttttttttttttttttttttttttttttcnbhnrox%257E001Nb0hZ_TAPP.iprice_TAPT.TI2%26trans_id%3D%257Btransaction_id%257D%26tclid%3Dca5add0c-9def-4d78-bf29-cdddd3defa5f&clickId=7bd9e6d6-c9da-4aa1-84cb-6ce402c46021&fullUrl=https%3A%2F%2Fti.ki%2F2sS%2F17FCWZZE%3Futm_term%3DTAPM.igttttttttttttttttttttttttttttttcnbhnrox%7E001Nb0hZ_TAPP.iprice_TAPT.TI2%26TIKI_URI%3Dhttps%253A%252F%252Ftiki.vn%252Fmay-xay-thit-xay-thuc-pham-da-nang-tefal-mb520138-hang-chinh-hang-p124116795.html%253Fspid%253D172920243%26utm_source%3Diprice%26trans_id%3D%257Btransaction_id%257D&isFBApp=false&deepLinkData=&hash=17FCWZZE"
            },
            {
                "product_name": "SYM Full bộ nồi( bộ côn ) trước dùng cho dòng xe máy tay ga Elites 50cc .",
                "product_price": 750000,
                "product_store": "Dung loc 1616310713",
                "product_image": "https://p-vn.ipricegroup.com/f095afb17e72aec758dae3e474ce8e8305887dcd_0.jpg",
                "product_link": "https://www.lazada.vn/products/full-bo-noi-bo-con-truoc-dung-cho-dong-xe-may-tay-ga-sym-elites-50cc-i2127180575-s10018067021.html?trafficFrom=17449020_303586&laz_trackid=2:mm_153090879_51752290_2010752336:clkgg5o4f1iha385krqdt2&mkttid=clkgg5o4f1iha385krqdt2"
            },
            {
                "product_name": "Starbucks Bộ Ly Giữ Nhiệt Valentine 591Ml",
                "product_price": 1200000,
                "product_store": "TieuyeuSbux",
                "product_image": "https://p-vn.ipricegroup.com/45b4fe096ff36ec8d42740116d9be402d057157d_0.jpg",
                "product_link": "https://shopee.vn/verify/traffic/error?home_url=https%3A%2F%2Fshopee.vn&is_logged_in=false&tracking_id=7267a4579a8-3d29-4d20-ad35-0f6a0d1f0112"
            },
            {
                "product_name": "Tupperware Chảo Mastro Frypan đáy 5 lớp",
                "product_price": 2699000,
                "product_store": "TupperwareVietNam",
                "product_image": "https://p-vn.ipricegroup.com/c26618ab670efab0225fad00745e9537cbfcffd0_0.jpg",
                "product_link": "https://www.lazada.vn/products/chao-mastro-frypan-tupperware-day-5-lop-i2423870208-s11952020114.html?trafficFrom=17449020_303586&laz_trackid=2:mm_150021224_51253421_2010203413:clkgg5ude1iha38qgisn6b&mkttid=clkgg5ude1iha38qgisn6b"
            },
            {
                "product_name": "Corelle [Mẫu Mới] Combo Bộ chén bát 59 món Thủy Tinh Mỹ French Blue",
                "product_price": 21465000,
                "product_store": "Công ty TNHH TM Quốc Tế T.M.T",
                "product_image": "https://p-vn.ipricegroup.com/615a43df66b97e67d1439ee29e1ef2283663a14c_0.jpg",
                "product_link": "https://www.lazada.vn/products/mau-moi-combo-bo-chen-bat-59-mon-thuy-tinh-my-corelle-french-blue-i2074179122-s9707496038.html?trafficFrom=17449020_303586&laz_trackid=2:mm_150021224_51253421_2010203413:clkgg5u631iha396aeqlkd&mkttid=clkgg5u631iha396aeqlkd"
            },
            {
                "product_name": "Zebra Chảo Inox Estio 3 Đáy 18Cm - 175088",
                "product_price": 472500,
                "product_store": "ZEBRA THÁI LAN",
                "product_image": "https://p-vn.ipricegroup.com/7a03e79427f508050e5dfe42ac58f087e563df32_0.jpg",
                "product_link": "https://shopee.vn/verify/traffic/error?home_url=https%3A%2F%2Fshopee.vn&is_logged_in=false&tracking_id=737095840f0-fccc-4ea6-a3c3-6a4025ff68c6"
            },
            {
                "product_name": "KIM HẰNG Nồi Nhôm Soup Pot (32-40Cm)",
                "product_price": 742000,
                "product_store": "NHÔM INOX KIM HẰNG",
                "product_image": "https://p-vn.ipricegroup.com/2b97a07e8712cf47d1481262a809112c8332a073_0.jpg",
                "product_link": "https://shopee.vn/verify/traffic/error?home_url=https%3A%2F%2Fshopee.vn&is_logged_in=false&tracking_id=600b240f3f0-0d63-488e-87a2-320c10ccdcf8"
            },
            {
                "product_name": "Khăn Trải Bàn Bằng Pvc Chống Thấm Nước / Dầu / Bỏng Tiện Dụng",
                "product_price": 130200,
                "product_store": "Creativehomelife.vn",
                "product_image": "https://p-vn.ipricegroup.com/b0d0e82fd7d827096e4b25fdc97593d9f7197dd9_0.jpg",
                "product_link": "https://shopee.vn/verify/traffic/error?home_url=https%3A%2F%2Fshopee.vn&is_logged_in=false&tracking_id=62200327644-c11a-47f7-95ef-84f12e30afa1"
            },
            {
                "product_name": "KIM HẰNG Bộ Nồi Nhôm+ Chảo Ceramic Chống Dính Sài Được Bếp Từ Nắp Kính Cường Lựcu",
                "product_price": 1122000,
                "product_store": "HÀNG CHÍNH HÃNG CÔNG TY",
                "product_image": "https://p-vn.ipricegroup.com/301bc4e798404644d62016b149ba4923547f8d28_0.jpg",
                "product_link": "https://shopee.vn/verify/traffic/error?home_url=https%3A%2F%2Fshopee.vn&is_logged_in=false&tracking_id=6159a9dbd37-8170-45ae-8eaf-3288888e64c8"
            },
            {
                "product_name": "Tupperware Chảo Universal Cookware Frypan 24cm nắp kính",
                "product_price": 1080000,
                "product_store": "TupperwareVietNam",
                "product_image": "https://p-vn.ipricegroup.com/625a89ae16ef3d15a8cacaceba367a77c3ab58a2_0.jpg",
                "product_link": "https://www.lazada.vn/products/chao-universal-cookware-frypan-24cm-nap-kinh-i1967612609-s12580303412.html?trafficFrom=17449020_303586&laz_trackid=2:mm_150021224_51253421_2010203413:clkgg5ufp1iha3an78t7nu&mkttid=clkgg5ufp1iha3an78t7nu"
            },
            {
                "product_name": "Starbucks Cốc sứ Been There 14oz (414ml)",
                "product_price": 170000,
                "product_store": "Starbucks tumbler 510",
                "product_image": "https://p-vn.ipricegroup.com/7029a73350b47db30d99823970f5d460c1c30a60_0.jpg",
                "product_link": "https://www.lazada.vn/products/coc-su-starbucks-been-there-14oz-414ml-i1394625684-s12585683776.html?trafficFrom=17449020_303586&laz_trackid=2:mm_150021224_51253421_2010203413:clkgikp0p1iha3b358aj77&mkttid=clkgikp0p1iha3b358aj77"
            },
            {
                "product_name": "SYM Bộ Nồi 110 Dùng Cho Các Dòng Xe Honda 100Cc-110Cc",
                "product_price": 1040000,
                "product_store": "PTXM858",
                "product_image": "https://p-vn.ipricegroup.com/b3b5f5568768ec0550226fa8df666d7e6eca6870_0.jpg",
                "product_link": "https://shopee.vn/verify/traffic/error?home_url=https%3A%2F%2Fshopee.vn&is_logged_in=false&tracking_id=732598deb63-615c-42e3-965c-58d0e65060f2"
            },
            {
                "product_name": "Starbucks |Chính Hãng| Trung Thu Mid Autumn - Bst Bình Ly Giữ Nhiệt Cốc, Bánh Trung Thu",
                "product_price": 820000,
                "product_store": "Starbuck Dreamers",
                "product_image": "https://p-vn.ipricegroup.com/d60f86521a63ef1550d5db1606833993d7bb32a0_0.jpg",
                "product_link": "https://shopee.vn/verify/traffic/error?home_url=https%3A%2F%2Fshopee.vn&is_logged_in=false&tracking_id=59257de615f-5aca-42d9-bb2e-e3ee0e6d2ac2"
            },
            {
                "product_name": "Zebra Bình giữ nhiệt Thái Lan Botto 07L (3 màu)-112642",
                "product_price": 379000,
                "product_store": "A Tan shop",
                "product_image": "https://p-vn.ipricegroup.com/86514089d38dd9a4efe4f967a205e4770775f49c_0.jpg",
                "product_link": "https://www.lazada.vn/products/binh-giu-nhiet-zebra-thai-lan-botto-07l-3-mau-112642-i1730344350-s7716878228.html?trafficFrom=17449020_303586&laz_trackid=2:mm_150021224_51253421_2010203413:clkgg5pif1iha3brf6ai6i&mkttid=clkgg5pif1iha3brf6ai6i"
            },
            {
                "product_name": "USA Home Set Bộ Bát Đĩa 12 Sản Phẩm Viền Vàng 22K Họa Tiết Hoa Vuông Thủy Tinh Ngọc Cao Cấp Nhập Khẩu Chính Hãng",
                "product_price": 1599312,
                "product_store": "Thủy tinh ngọc MP-USA Homeset",
                "product_image": "https://p-vn.ipricegroup.com/58dda0ce2c9e20c574620a1f0a938cd1685c3ada_0.jpg",
                "product_link": "https://shopee.vn/verify/traffic/error?home_url=https%3A%2F%2Fshopee.vn&is_logged_in=false&tracking_id=7758578ee4b-36e9-4f7e-805b-cf3374076b3c"
            },
            {
                "product_name": "Corelle Dĩa Oval Thủy Tinh Mỹ Provence Garden 32cm 611-PVG-LP",
                "product_price": 590000,
                "product_store": "Công ty TNHH TM Quốc Tế T.M.T",
                "product_image": "https://p-vn.ipricegroup.com/7bb4f8e2c41087ee86d5f908c6c3862a5de53902_0.jpg",
                "product_link": "https://www.lazada.vn/products/dia-oval-thuy-tinh-my-corelle-provence-garden-32cm-611-pvg-lp-i2074028824-s9707381519.html?trafficFrom=17449020_303586&laz_trackid=2:mm_150021224_51253421_2010203413:clkgl3v381iha3cfpdt6ps&mkttid=clkgl3v381iha3cfpdt6ps"
            },
            {
                "product_name": "Tupperware Ly Giữ Nhiệt Xploris Chính Hãng Xanh Nhạt 230Ml",
                "product_price": 690000,
                "product_store": "Tiệm Chạp Phô Tháng 10",
                "product_image": "https://p-vn.ipricegroup.com/4766758ae9b92de41409ce7cc1928cebacc64530_0.jpg",
                "product_link": "https://tiki.vn/ly-giu-nhiet-xploris-tupperware-chinh-hang-xanh-nhat-230ml-p262991451.html?spid=262991453&utm_source=iprice.vn&utm_medium=tiki-aff&utm_campaign=AFF_NBR_IPR_UNK_TIKIVN-17FCWZZE_ALL_VN_ALL_UNK_UNK_TAPX.58f86df1-beb8-498c-b56f-1565af399ec0_TAPU.9cbabb48-212d-4930-bef0-ae555f53d833&utm_term=TAPM.igttttttttttttttttttttttttttttttiuno1tt%7E%7E001IM0hZ_TAPP.iprice_TAPT.TI2&trans_id=%7Btransaction_id%7D&tclid=0b91b2c9-d006-4539-8da4-3e5e61e2c42c&fsl=true&isOpenStore=false&trackId=67821a367a1c5eee7dae173b&osName=Windows&deepLink=tikivn%3A%2F%2Fproducts%2F262991451%3Fspid%3D262991453%26utm_source%3Diprice.vn%26utm_medium%3Dtiki-aff%26utm_campaign%3DAFF_NBR_IPR_UNK_TIKIVN-17FCWZZE_ALL_VN_ALL_UNK_UNK_TAPX.58f86df1-beb8-498c-b56f-1565af399ec0_TAPU.9cbabb48-212d-4930-bef0-ae555f53d833%26utm_term%3DTAPM.igttttttttttttttttttttttttttttttiuno1tt%257E%257E001IM0hZ_TAPP.iprice_TAPT.TI2%26trans_id%3D%257Btransaction_id%257D%26tclid%3D0b91b2c9-d006-4539-8da4-3e5e61e2c42c&clickId=823b1a6c-97b2-407a-8ed5-74c50628a17e&fullUrl=https%3A%2F%2Fti.ki%2F2sS%2F17FCWZZE%3Futm_term%3DTAPM.igttttttttttttttttttttttttttttttiuno1tt%7E%7E001IM0hZ_TAPP.iprice_TAPT.TI2%26TIKI_URI%3Dhttps%253A%252F%252Ftiki.vn%252Fly-giu-nhiet-xploris-tupperware-chinh-hang-xanh-nhat-230ml-p262991451.html%253Fspid%253D262991453%26utm_source%3Diprice%26trans_id%3D%257Btransaction_id%257D&isFBApp=false&deepLinkData=&hash=17FCWZZE"
            },
            {
                "product_name": "KIM HẰNG Chảo/Quánh Chống Dính Quantum Usa 22-30 Cm",
                "product_price": 213000,
                "product_store": "NHÔM INOX KIM HẰNG",
                "product_image": "https://p-vn.ipricegroup.com/6027c1821a3b7b6d3e7c61d2159df3dc5ff017de_0.jpg",
                "product_link": "https://shopee.vn/verify/traffic/error?home_url=https%3A%2F%2Fshopee.vn&is_logged_in=false&tracking_id=785e05f0a5d-fff3-4013-be55-5c9a74c4c6c2"
            },
            {
                "product_name": "Zebra Bộ Nồi 3 Đáy Extra Infinity Ii (16Cm - 18Cm - 20Cm) - 180828 - Mẫu Nhỏ Gọn Mới Nhất 2024",
                "product_price": 1086000,
                "product_store": "GIA DỤNG THÀNH LỘC",
                "product_image": "https://p-vn.ipricegroup.com/7b7f3efbfa4f0355347ffd655f44188bbd6fd225_0.jpg",
                "product_link": "https://shopee.vn/verify/traffic/error?home_url=https%3A%2F%2Fshopee.vn&is_logged_in=false&tracking_id=64575df8ad2-971a-4f27-98ad-667562848a3c"
            },
            {
                "product_name": "Corelle Tô Thủy Tinh Mỹ Elegant City 473Ml 416-Ec",
                "product_price": 380000,
                "product_store": "Cty Thương Mại Quốc Tế T.M.T",
                "product_image": "https://p-vn.ipricegroup.com/4c4a49168eac9393e09ba6ebb815c37f1c9bbed2_0.jpg",
                "product_link": "https://shopee.vn/verify/traffic/error?home_url=https%3A%2F%2Fshopee.vn&is_logged_in=false&tracking_id=60941390ed8-d378-484c-a023-2589bc0c7c92"
            },
            {
                "product_name": "Duy Tân [HCM]Kệ chén nhựa LỚN 3 ngăn-4 tầng- KT- 59.5 x 40.5 x 121 cm",
                "product_price": 650000,
                "product_store": "Trusted brand",
                "product_image": "https://p-vn.ipricegroup.com/4fc8b88d601bfa60a4c93f72239241e39f5e8a63_0.jpg",
                "product_link": "https://www.lazada.vn/products/hcmke-chen-nhua-duy-tan-lon-3-ngan-4-tang-kt-595-x-405-x-121-cm-i792366846-s2138060168.html?trafficFrom=17449020_303586&laz_trackid=2:mm_150021224_51253421_2010203413:clkgl3pjt1iha3ds0mrpvv&mkttid=clkgl3pjt1iha3ds0mrpvv"
            },
            {
                "product_name": "Starbucks Ly Giữ Nhiệt Dion Omber Pinks",
                "product_price": 1150000,
                "product_store": "TieuyeuSbux",
                "product_image": "https://p-vn.ipricegroup.com/6d9c7ecf351a96f3bad4a188cee4d83135e56d1b_0.jpg",
                "product_link": "https://shopee.vn/verify/traffic/error?home_url=https%3A%2F%2Fshopee.vn&is_logged_in=false&tracking_id=60221fcce95-d74e-41da-aa0a-0311a9ce0e5c"
            },
            {
                "product_name": "20 GÓI KHĂN GIẤY ĂN GẤU TRÚC SIPIAO - KHĂN GIẤY CAO CẤP MỖI GÓI 300 TỜ - NHỎ GỌN TIỆN LỢI AN TOÀN DỄ SỬ DỤNG",
                "product_price": 54300,
                "product_store": "khanuotvietkids.Selection",
                "product_image": "https://p-vn.ipricegroup.com/e888ea681e3d6936e0d1429b2e21096a1adf8652_0.jpg",
                "product_link": "https://www.lazada.vn/products/20-goi-khan-giay-an-gau-truc-sipiao-khan-giay-cao-cap-moi-goi-300-to-nho-gon-tien-loi-an-toan-de-su-dung-i2629936987-s12838249303.html?trafficFrom=17449020_303586&laz_trackid=2:mm_150021224_51253421_2010203413:clkgikv4a1iha3efrnu4hr&mkttid=clkgikv4a1iha3efrnu4hr"
            },
            {
                "product_name": "Akatsu Dao Thái Lọc Thịt -Hàng Chuẩn Nhật, Thép Không Han Rỉ Siêu Sắc Bén",
                "product_price": 225000,
                "product_store": "Shop đồ gia dụng bếp",
                "product_image": "https://p-vn.ipricegroup.com/0d98c4b52a96a203ef327e0ade607fd38600bead_0.jpg",
                "product_link": "https://shopee.vn/verify/traffic/error?home_url=https%3A%2F%2Fshopee.vn&is_logged_in=false&tracking_id=879d1e76b9a-8ef5-4277-b58e-d68fee1cd420"
            },
            {
                "product_name": "KIM HẰNG [Chính Hãng] Chảo Bầu Chống Dính Cao Cấp Nhôm ( Size 22 26 30)",
                "product_price": 210000,
                "product_store": "KIM HẰNG HOUSE",
                "product_image": "https://p-vn.ipricegroup.com/89a75189aeb76eaa24f1da48d08e506cf4f30052_0.jpg",
                "product_link": "https://shopee.vn/verify/traffic/error?home_url=https%3A%2F%2Fshopee.vn&is_logged_in=false&tracking_id=6347af197e2-825b-4cae-865b-35d2e4323c65"
            },
            {
                "product_name": "Starbucks [Authentic] LY GIỮ NHIỆT DION COLD CUP GRADIENT GREEN 591ML",
                "product_price": 1140000,
                "product_store": "Goblin Starbucks Store",
                "product_image": "https://p-vn.ipricegroup.com/37aad1a214ac305a78d7a3b39b8734214918fc80_0.jpg",
                "product_link": "https://www.lazada.vn/products/authentic-starbucks-ly-giu-nhiet-dion-cold-cup-gradient-green-591ml-i2501729094-s12265210650.html?trafficFrom=17449020_303586&laz_trackid=2:mm_150021224_51253421_2010203413:clkgg5ude1iha3fdk0uc6h&mkttid=clkgg5ude1iha3fdk0uc6h"
            },
            {
                "product_name": "Corelle [Mẫu Mới] Tô Thủy Tinh Mỹ Greenery Wedding (White Rose-Hoa Hồng Trắng) 432V-Gwd Dòng Gold Tem Vàng",
                "product_price": 490000,
                "product_store": "Cty Thương Mại Quốc Tế T.M.T",
                "product_image": "https://p-vn.ipricegroup.com/ed3dc96ff2110b99a344f78cf2155c93c8aef046_0.jpg",
                "product_link": "https://shopee.vn/verify/traffic/error?home_url=https%3A%2F%2Fshopee.vn&is_logged_in=false&tracking_id=619eec66892-cbd4-40ca-b716-7a95fcec46af"
            },
            {
                "product_name": "DUY TAN Kệ Úp Chén 4 Tầng Lớn Duy Tân",
                "product_price": 215800,
                "product_store": "Lam Anh (LA)",
                "product_image": "https://p-vn.ipricegroup.com/ddf3ec43551c18a3a3766246a7f70bfc49a44206_0.jpg",
                "product_link": "https://shopee.vn/verify/traffic/error?home_url=https%3A%2F%2Fshopee.vn&is_logged_in=false&tracking_id=6213194a760-8ef4-4177-92c0-e1e99bb09364"
            },
            {
                "product_name": "Zebra Dao Chặt Xương Lớn Chef 7,5; - 100261",
                "product_price": 263000,
                "product_store": "giadungnhapkhautt",
                "product_image": "https://p-vn.ipricegroup.com/57213f1fa8684887bc9fa0adb0b6507f3910615e_0.jpg",
                "product_link": "https://shopee.vn/verify/traffic/error?home_url=https%3A%2F%2Fshopee.vn&is_logged_in=false&tracking_id=635f346b558-0bc6-4916-a01d-8bf4044fe791"
            }
        ],
        "sub_categories": []
    }
]